ConglingkaishiDeUefiLuojiBianchengFix1/README.md
ConglingkaishiDeUefiLuojiBianchengFix1/__init__.py
ConglingkaishiDeUefiLuojiBianchengFix1/__main__.py
ConglingkaishiDeUefiLuojiBianchengFix1/file.epub
ConglingkaishiDeUefiLuojiBianchengFix1/index.html
ConglingkaishiDeUefiLuojiBianchengFix1/css/__init__.py
ConglingkaishiDeUefiLuojiBianchengFix1/css/annotations.css
ConglingkaishiDeUefiLuojiBianchengFix1/css/main.css
ConglingkaishiDeUefiLuojiBianchengFix1/css/normalize.css
ConglingkaishiDeUefiLuojiBianchengFix1/css/popup.css
ConglingkaishiDeUefiLuojiBianchengFix1/font/__init__.py
ConglingkaishiDeUefiLuojiBianchengFix1/font/fontello.eot
ConglingkaishiDeUefiLuojiBianchengFix1/font/fontello.svg
ConglingkaishiDeUefiLuojiBianchengFix1/font/fontello.ttf
ConglingkaishiDeUefiLuojiBianchengFix1/font/fontello.woff
ConglingkaishiDeUefiLuojiBianchengFix1/img/__init__.py
ConglingkaishiDeUefiLuojiBianchengFix1/img/annotator-glyph-sprite.png
ConglingkaishiDeUefiLuojiBianchengFix1/img/annotator-icon-sprite.png
ConglingkaishiDeUefiLuojiBianchengFix1/img/apple-touch-icon.png
ConglingkaishiDeUefiLuojiBianchengFix1/img/cancelfullscreen.png
ConglingkaishiDeUefiLuojiBianchengFix1/img/close.png
ConglingkaishiDeUefiLuojiBianchengFix1/img/fullscreen.png
ConglingkaishiDeUefiLuojiBianchengFix1/img/loader.gif
ConglingkaishiDeUefiLuojiBianchengFix1/img/menu-icon.png
ConglingkaishiDeUefiLuojiBianchengFix1/img/save.png
ConglingkaishiDeUefiLuojiBianchengFix1/img/saved.png
ConglingkaishiDeUefiLuojiBianchengFix1/img/settings-s.png
ConglingkaishiDeUefiLuojiBianchengFix1/img/settings.png
ConglingkaishiDeUefiLuojiBianchengFix1/img/star.png
ConglingkaishiDeUefiLuojiBianchengFix1/js/__init__.py
ConglingkaishiDeUefiLuojiBianchengFix1/js/epub.js
ConglingkaishiDeUefiLuojiBianchengFix1/js/epub.min.js
ConglingkaishiDeUefiLuojiBianchengFix1/js/epub.min.map
ConglingkaishiDeUefiLuojiBianchengFix1/js/hooks.min.js
ConglingkaishiDeUefiLuojiBianchengFix1/js/hooks.min.map
conglingkaishi_de_uefi_luoji_biancheng_fix1-2025.3.25.0.dist-info/METADATA
conglingkaishi_de_uefi_luoji_biancheng_fix1-2025.3.25.0.dist-info/WHEEL
conglingkaishi_de_uefi_luoji_biancheng_fix1-2025.3.25.0.dist-info/entry_points.txt
conglingkaishi_de_uefi_luoji_biancheng_fix1-2025.3.25.0.dist-info/top_level.txt
conglingkaishi_de_uefi_luoji_biancheng_fix1-2025.3.25.0.dist-info/RECORD
